BayesianBrandTracker/BTModel.py
BayesianBrandTracker/__init__.py
BayesianBrandTracker/_modidx.py
BayesianBrandTracker-0.0.1.dist-info/LICENSE
BayesianBrandTracker-0.0.1.dist-info/METADATA
BayesianBrandTracker-0.0.1.dist-info/WHEEL
BayesianBrandTracker-0.0.1.dist-info/entry_points.txt
BayesianBrandTracker-0.0.1.dist-info/top_level.txt
BayesianBrandTracker-0.0.1.dist-info/RECORD
