Metadata-Version: 2.1
Name: BayesianBrandTracker
Version: 0.0.1
Summary: A bayesian approach to brand health tracking
Home-page: https://github.com/redam94/BayesianBrandTracker
Author: Matthew Reda
Author-email: m.reda94@gmail.com
License: Apache Software License 2.0
Keywords: nbdev jupyter notebook python
Classifier: Development Status :: 4 - Beta
Classifier: Intended Audience :: Developers
Classifier: Natural Language :: English
Classifier: Programming Language :: Python :: 3.7
Classifier: Programming Language :: Python :: 3.8
Classifier: Programming Language :: Python :: 3.9
Classifier: Programming Language :: Python :: 3.10
Classifier: Programming Language :: Python :: 3.11
Classifier: Programming Language :: Python :: 3.12
Classifier: License :: OSI Approved :: Apache Software License
Requires-Python: >=3.7
License-File: LICENSE
Requires-Dist: fastcore
Requires-Dist: pandas
Requires-Dist: xarray
Requires-Dist: pymc
Requires-Dist: numpy
Provides-Extra: dev
